<?xml version="1.0" encoding="UTF-8"?>
<!DOCTYPE mapper PUBLIC "-//mybatis.org//DTD Mapper 3.0//EN" "http://mybatis.org/dtd/mybatis-3-mapper.dtd">

<mapper namespace="kr.co.platform.api.sign.dao.ApiSignDAO">
	
	<resultMap type="kr.co.platform.api.sign.dto.Member" id="Members">
		<result column="reg_no" property="reg_no" />
		<result column="member_id" property="id" />
		<result column="member_password" property="password" />
		<result column="authority_level" property="authority_level" />
		<result column="member_name" property="name" />
		<result column="member_email" property="email" />
		<result column="member_mobile" property="mobile" />
	</resultMap>
	
	<select id="selectUserInfoById" 
		parameterType="kr.co.platform.api.sign.dto.Member" 
		resultMap="Members">
		SELECT
			reg_no,
			member_id,
			member_password,
			authority_level,
			member_name,
			member_email,
			member_mobile,
			DATE_FORMAT(last_login_dt, '%Y.%m.%d %H:%i:%s') AS last_login_dt
		FROM
			members
		WHERE
			member_id = #{id}
			AND is_deleted != 'Y'
	</select>
	
	<insert id="insertUserInfo" parameterType="kr.co.platform.api.sign.dto.Member">
		INSERT INTO members (
			member_id, member_password, authority_level, member_name,
			member_email, member_mobile, reg_date
		) VALUES (
			#{id}, #{enc_password}, #{authority_level}, #{name},
			#{email}, #{mobile}, NOW()
		)	
	</insert>
		
</mapper>